ml4e/__init__.py
ml4e/main.py
ml4e-0.0.2.dist-info/LICENSE
ml4e-0.0.2.dist-info/METADATA
ml4e-0.0.2.dist-info/WHEEL
ml4e-0.0.2.dist-info/top_level.txt
ml4e-0.0.2.dist-info/RECORD
