Metadata-Version: 2.1
Name: ml4e
Version: 0.0.2
Summary: Home for state-of-art ML Models.
Home-page: https://github.com/Machine-Learning-for-Everyone-ML4E/ml4e
License-File: LICENSE
